fgclip_mcp/__init__.py
fgclip_mcp/__main__.py
fgclip_mcp/config.py
fgclip_mcp/embedding_client.py
fgclip_mcp/embedding_storage.py
fgclip_mcp/exceptions.py
fgclip_mcp/logging_config.py
fgclip_mcp/server.py
fgclip_mcp/tools.py
fgclip_mcp-0.1.2.dist-info/METADATA
fgclip_mcp-0.1.2.dist-info/WHEEL
fgclip_mcp-0.1.2.dist-info/entry_points.txt
fgclip_mcp-0.1.2.dist-info/licenses/LICENSE
fgclip_mcp-0.1.2.dist-info/RECORD
